commonroad_idm_planner/__init__.py
commonroad_idm_planner/base_planner.py
commonroad_idm_planner/configuration/__init__.py
commonroad_idm_planner/configuration/planner_config.py
commonroad_idm_planner/idm_easy_api.py
commonroad_idm_planner/idm_input.py
commonroad_idm_planner/idm_path.py
commonroad_idm_planner/idm_planner.py
commonroad_idm_planner/idm_state.py
commonroad_idm_planner/idm_trajectory.py
commonroad_idm_planner/scenario_verification/__init__.py
commonroad_idm_planner/scenario_verification/scenario_fixer.py
commonroad_idm_planner/scenario_verification/scenario_verifier.py
commonroad_idm_planner/util/__init__.py
commonroad_idm_planner/util/closest_obstacle.py
commonroad_idm_planner/util/collision/__init__.py
commonroad_idm_planner/util/collision/collision_checks.py
commonroad_idm_planner/util/collision/collision_status.py
commonroad_idm_planner/util/geometry.py
commonroad_idm_planner/util/goal_util.py
commonroad_idm_planner/util/pp_util.py
commonroad_idm_planner/util/velocity_planning.py
commonroad_idm_planner/util/visualization/__init__.py
commonroad_idm_planner/util/visualization/visualize_inputs.py
commonroad_idm_planner/util/visualization/visualize_physics.py
commonroad_idm_planner/util/visualization/visualize_scenario.py
commonroad_idm_planner-0.2.1.dist-info/METADATA
commonroad_idm_planner-0.2.1.dist-info/WHEEL
commonroad_idm_planner-0.2.1.dist-info/licenses/LICENSE
commonroad_idm_planner-0.2.1.dist-info/RECORD
