Metadata-Version: 2.4
Name: commonroad-idm-planner
Version: 0.2.1
Summary: CommonRoad Intelligent Driver Model Planner
License: BSD
License-File: LICENSE
Keywords: autonomous,automated,vehicles,driving,motion,planning
Author: Tobias Mascetta
Author-email: <tobias.mascetta@tum.de>
Requires-Python: >=3.9, < 3.12
Classifier: Programming Language :: Python :: 3.9
Classifier: Programming Language :: Python :: 3.10
Classifier: Programming Language :: Python :: 3.11
Classifier: License :: OSI Approved :: BSD License
Classifier: Operating System :: POSIX :: Linux
Requires-Dist: commonroad-drivability-checker (>=2025.1.0,<2026.0.0)
Requires-Dist: commonroad-io (>=2022.2,<2025.0.1)
Requires-Dist: commonroad-route-planner (>=2025.0.1,<2026.0.1)
Requires-Dist: matplotlib (>=3.9)
Requires-Dist: numpy (>=2.0)
